cz_gitmoji/__init__.py
cz_gitmoji/conventional_gitmojis_info.txt
cz_gitmoji/main.py
cz_gitmoji/py.typed
gitmojify/__init__.py
gitmojify/mojify.py
gitmojify/py.typed
shared/__init__.py
shared/gitmojis.py
shared/model.py
shared/py.typed
shared/settings.py
shared/spec.py
shared/utils.py
cz_conventional_gitmoji-0.7.0.dist-info/METADATA
cz_conventional_gitmoji-0.7.0.dist-info/WHEEL
cz_conventional_gitmoji-0.7.0.dist-info/entry_points.txt
cz_conventional_gitmoji-0.7.0.dist-info/RECORD
