Metadata-Version: 2.4
Name: cz-conventional-gitmoji
Version: 0.7.0
Summary: A commitizen plugin that combines gitmoji and conventional.
Author-email: ljnsn <info@ljnsn.com>
License-Expression: MIT
Requires-Python: >=3.8
Requires-Dist: attrs>=23.1.0
Requires-Dist: commitizen>=3.9.1
